tcap/__init__.py
tcap/chapter_messages.py
tcap/run_full_cycle.py
tcap/run_the_full_process.py
tcap/util.py
tcap/applications/__init__.py
tcap/applications/main.py
tcap/applications/sanity/__init__.py
tcap/applications/sanity/model_perf.py
tcap/applications/sanity/pre_model_analysis.py
tcap/applications/sanity/run_the_full_process.py
tcap/applications/sanity/teacup.py
tcap/cleaning/__init__.py
tcap/cleaning/cleaning_func.py
tcap/cleaning/file.py
tcap/data_loader/__init__.py
tcap/data_loader/webtext_data.py
tcap/feature_analyzing/__init__.py
tcap/feature_analyzing/feature_correlation.py
tcap/feature_analyzing/imported.py
tcap/features_engineering/__init__.py
tcap/features_engineering/bag_of_words.py
tcap/features_engineering/corex.py
tcap/features_engineering/feature_main.py
tcap/features_engineering/tfidf.py
tcap/model_analyzer/__init__.py
tcap/model_analyzer/model_analysis.py
tcap/model_compare/__init__.py
tcap/model_compare/compare_messages.py
tcap/model_compare/models_comparison.py
tcap/model_hp_optimization/__init__.py
tcap/model_hp_optimization/hp_space.py
tcap/model_hp_optimization/optimization_algorithm.py
tcap/model_training/__init__.py
tcap/model_training/best_model.py
tcap/model_training/data_preparation.py
tcap/model_training/model_utils.py
tcap/model_training/models/__init__.py
tcap/model_training/models/baseline_model.py
tcap/model_training/models/cv_training.py
tcap/model_training/models/lgbm_class.py
tcap/model_training/models/logistic_regression.py
tcap/model_training/models/lstm.py
tcap/model_training/models/model_input_and_output_classes.py
tcap/model_training/models/scoring.py
tcap/preprocessing/__init__.py
tcap/preprocessing/preprocessing_func.py
tcap/text_analyzer/__init__.py
tcap/text_analyzer/common_words.py
tcap/text_analyzer/corex_topics.py
tcap/text_analyzer/data_quality.py
tcap/text_analyzer/key_sentences.py
tcap/text_analyzer/keywords_extraction.py
tcap/text_analyzer/sentiment.py
tcap/text_analyzer/smart_text_analyzer.py
tcap-2.23.dist-info/METADATA
tcap-2.23.dist-info/WHEEL
tcap-2.23.dist-info/top_level.txt
tcap-2.23.dist-info/RECORD
